setup.py
rhoPorousSimpleFlux/__init__.py
rhoPorousSimpleFlux.egg-info/PKG-INFO
rhoPorousSimpleFlux.egg-info/SOURCES.txt
rhoPorousSimpleFlux.egg-info/dependency_links.txt
rhoPorousSimpleFlux.egg-info/entry_points.txt
rhoPorousSimpleFlux.egg-info/requires.txt
rhoPorousSimpleFlux.egg-info/top_level.txt
rhoPorousSimpleFlux.egg-info/zip-safe
rhoPorousSimpleFlux/r1_4_1_dev/__init__.py
rhoPorousSimpleFlux/r1_5/__init__.py
rhoPorousSimpleFlux/r1_6/__init__.py
rhoPorousSimpleFlux/r1_6_dev/__init__.py
rhoPorousSimpleFlux/r1_7_0/__init__.py